{
  "name": "@kickstartds/storyblok-example",
  "entries": [
    {
      "version": "2.0.25",
      "tag": "@kickstartds/storyblok-example_v2.0.25",
      "date": "Wed, 10 Jul 2024 12:46:32 GMT",
      "comments": {
        "dependency": [
          {
            "comment": "Updating dependency \"@kickstartds/jsonschema-utils\" to `3.3.3`"
          },
          {
            "comment": "Updating dependency \"@kickstartds/jsonschema2storyblok\" to `1.5.33`"
          }
        ]
      }
    },
    {
      "version": "2.0.24",
      "tag": "@kickstartds/storyblok-example_v2.0.24",
      "date": "Tue, 09 Jul 2024 11:13:35 GMT",
      "comments": {
        "dependency": [
          {
            "comment": "Updating dependency \"@kickstartds/jsonschema-utils\" to `3.3.2`"
          },
          {
            "comment": "Updating dependency \"@kickstartds/jsonschema2storyblok\" to `1.5.32`"
          }
        ]
      }
    },
    {
      "version": "2.0.23",
      "tag": "@kickstartds/storyblok-example_v2.0.23",
      "date": "Tue, 09 Jul 2024 10:38:59 GMT",
      "comments": {
        "dependency": [
          {
            "comment": "Updating dependency \"@kickstartds/jsonschema-utils\" to `3.3.1`"
          },
          {
            "comment": "Updating dependency \"@kickstartds/jsonschema2storyblok\" to `1.5.31`"
          }
        ]
      }
    },
    {
      "version": "2.0.22",
      "tag": "@kickstartds/storyblok-example_v2.0.22",
      "date": "Fri, 05 Jul 2024 14:49:28 GMT",
      "comments": {
        "dependency": [
          {
            "comment": "Updating dependency \"@kickstartds/jsonschema-utils\" to `3.3.0`"
          },
          {
            "comment": "Updating dependency \"@kickstartds/jsonschema2storyblok\" to `1.5.30`"
          }
        ]
      }
    },
    {
      "version": "2.0.21",
      "tag": "@kickstartds/storyblok-example_v2.0.21",
      "date": "Fri, 28 Jun 2024 15:41:22 GMT",
      "comments": {
        "dependency": [
          {
            "comment": "Updating dependency \"@kickstartds/jsonschema-utils\" to `3.2.0`"
          },
          {
            "comment": "Updating dependency \"@kickstartds/jsonschema2storyblok\" to `1.5.29`"
          }
        ]
      }
    },
    {
      "version": "2.0.20",
      "tag": "@kickstartds/storyblok-example_v2.0.20",
      "date": "Tue, 25 Jun 2024 10:40:59 GMT",
      "comments": {
        "dependency": [
          {
            "comment": "Updating dependency \"@kickstartds/jsonschema-utils\" to `3.1.2`"
          },
          {
            "comment": "Updating dependency \"@kickstartds/jsonschema2storyblok\" to `1.5.28`"
          }
        ]
      }
    },
    {
      "version": "2.0.19",
      "tag": "@kickstartds/storyblok-example_v2.0.19",
      "date": "Tue, 25 Jun 2024 10:33:43 GMT",
      "comments": {
        "dependency": [
          {
            "comment": "Updating dependency \"@kickstartds/jsonschema-utils\" to `3.1.1`"
          },
          {
            "comment": "Updating dependency \"@kickstartds/jsonschema2storyblok\" to `1.5.27`"
          }
        ]
      }
    },
    {
      "version": "2.0.18",
      "tag": "@kickstartds/storyblok-example_v2.0.18",
      "date": "Tue, 25 Jun 2024 09:46:26 GMT",
      "comments": {
        "dependency": [
          {
            "comment": "Updating dependency \"@kickstartds/jsonschema-utils\" to `3.1.0`"
          },
          {
            "comment": "Updating dependency \"@kickstartds/jsonschema2storyblok\" to `1.5.26`"
          }
        ]
      }
    },
    {
      "version": "2.0.17",
      "tag": "@kickstartds/storyblok-example_v2.0.17",
      "date": "Mon, 24 Jun 2024 10:40:19 GMT",
      "comments": {
        "dependency": [
          {
            "comment": "Updating dependency \"@kickstartds/jsonschema-utils\" to `3.0.16`"
          },
          {
            "comment": "Updating dependency \"@kickstartds/jsonschema2storyblok\" to `1.5.25`"
          }
        ]
      }
    },
    {
      "version": "2.0.16",
      "tag": "@kickstartds/storyblok-example_v2.0.16",
      "date": "Wed, 17 Apr 2024 18:29:14 GMT",
      "comments": {
        "dependency": [
          {
            "comment": "Updating dependency \"@kickstartds/jsonschema-utils\" to `3.0.15`"
          },
          {
            "comment": "Updating dependency \"@kickstartds/jsonschema2storyblok\" to `1.5.24`"
          }
        ]
      }
    },
    {
      "version": "2.0.15",
      "tag": "@kickstartds/storyblok-example_v2.0.15",
      "date": "Wed, 17 Apr 2024 13:59:55 GMT",
      "comments": {
        "dependency": [
          {
            "comment": "Updating dependency \"@kickstartds/jsonschema-utils\" to `3.0.14`"
          },
          {
            "comment": "Updating dependency \"@kickstartds/jsonschema2storyblok\" to `1.5.23`"
          }
        ]
      }
    },
    {
      "version": "2.0.14",
      "tag": "@kickstartds/storyblok-example_v2.0.14",
      "date": "Mon, 15 Apr 2024 13:24:51 GMT",
      "comments": {
        "dependency": [
          {
            "comment": "Updating dependency \"@kickstartds/jsonschema-utils\" to `3.0.13`"
          },
          {
            "comment": "Updating dependency \"@kickstartds/jsonschema2storyblok\" to `1.5.22`"
          }
        ]
      }
    },
    {
      "version": "2.0.13",
      "tag": "@kickstartds/storyblok-example_v2.0.13",
      "date": "Mon, 15 Apr 2024 13:21:12 GMT",
      "comments": {
        "dependency": [
          {
            "comment": "Updating dependency \"@kickstartds/jsonschema-utils\" to `3.0.12`"
          },
          {
            "comment": "Updating dependency \"@kickstartds/jsonschema2storyblok\" to `1.5.21`"
          }
        ]
      }
    },
    {
      "version": "2.0.12",
      "tag": "@kickstartds/storyblok-example_v2.0.12",
      "date": "Thu, 11 Apr 2024 08:42:25 GMT",
      "comments": {
        "dependency": [
          {
            "comment": "Updating dependency \"@kickstartds/jsonschema2storyblok\" to `1.5.20`"
          }
        ]
      }
    },
    {
      "version": "2.0.11",
      "tag": "@kickstartds/storyblok-example_v2.0.11",
      "date": "Wed, 20 Mar 2024 20:13:09 GMT",
      "comments": {
        "dependency": [
          {
            "comment": "Updating dependency \"@kickstartds/jsonschema-utils\" to `3.0.11`"
          },
          {
            "comment": "Updating dependency \"@kickstartds/jsonschema2storyblok\" to `1.5.19`"
          }
        ]
      }
    },
    {
      "version": "2.0.10",
      "tag": "@kickstartds/storyblok-example_v2.0.10",
      "date": "Wed, 20 Mar 2024 14:13:07 GMT",
      "comments": {
        "dependency": [
          {
            "comment": "Updating dependency \"@kickstartds/jsonschema-utils\" to `3.0.10`"
          },
          {
            "comment": "Updating dependency \"@kickstartds/jsonschema2storyblok\" to `1.5.18`"
          }
        ]
      }
    },
    {
      "version": "2.0.9",
      "tag": "@kickstartds/storyblok-example_v2.0.9",
      "date": "Mon, 18 Mar 2024 16:21:35 GMT",
      "comments": {
        "dependency": [
          {
            "comment": "Updating dependency \"@kickstartds/jsonschema-utils\" to `3.0.9`"
          },
          {
            "comment": "Updating dependency \"@kickstartds/jsonschema2storyblok\" to `1.5.17`"
          }
        ]
      }
    },
    {
      "version": "2.0.8",
      "tag": "@kickstartds/storyblok-example_v2.0.8",
      "date": "Mon, 18 Mar 2024 16:16:53 GMT",
      "comments": {
        "dependency": [
          {
            "comment": "Updating dependency \"@kickstartds/jsonschema-utils\" to `3.0.8`"
          },
          {
            "comment": "Updating dependency \"@kickstartds/jsonschema2storyblok\" to `1.5.16`"
          }
        ]
      }
    },
    {
      "version": "2.0.7",
      "tag": "@kickstartds/storyblok-example_v2.0.7",
      "date": "Mon, 18 Mar 2024 15:09:15 GMT",
      "comments": {
        "dependency": [
          {
            "comment": "Updating dependency \"@kickstartds/jsonschema-utils\" to `3.0.7`"
          },
          {
            "comment": "Updating dependency \"@kickstartds/jsonschema2storyblok\" to `1.5.15`"
          }
        ]
      }
    },
    {
      "version": "2.0.6",
      "tag": "@kickstartds/storyblok-example_v2.0.6",
      "date": "Mon, 18 Mar 2024 13:53:57 GMT",
      "comments": {
        "dependency": [
          {
            "comment": "Updating dependency \"@kickstartds/jsonschema-utils\" to `3.0.6`"
          },
          {
            "comment": "Updating dependency \"@kickstartds/jsonschema2storyblok\" to `1.5.14`"
          }
        ]
      }
    },
    {
      "version": "2.0.5",
      "tag": "@kickstartds/storyblok-example_v2.0.5",
      "date": "Mon, 18 Mar 2024 10:56:30 GMT",
      "comments": {
        "dependency": [
          {
            "comment": "Updating dependency \"@kickstartds/jsonschema-utils\" to `3.0.5`"
          },
          {
            "comment": "Updating dependency \"@kickstartds/jsonschema2storyblok\" to `1.5.13`"
          }
        ]
      }
    },
    {
      "version": "2.0.4",
      "tag": "@kickstartds/storyblok-example_v2.0.4",
      "date": "Thu, 14 Mar 2024 14:00:48 GMT",
      "comments": {
        "dependency": [
          {
            "comment": "Updating dependency \"@kickstartds/jsonschema-utils\" to `3.0.4`"
          },
          {
            "comment": "Updating dependency \"@kickstartds/jsonschema2storyblok\" to `1.5.12`"
          }
        ]
      }
    },
    {
      "version": "2.0.3",
      "tag": "@kickstartds/storyblok-example_v2.0.3",
      "date": "Thu, 14 Mar 2024 13:50:59 GMT",
      "comments": {
        "dependency": [
          {
            "comment": "Updating dependency \"@kickstartds/jsonschema-utils\" to `3.0.3`"
          },
          {
            "comment": "Updating dependency \"@kickstartds/jsonschema2storyblok\" to `1.5.11`"
          }
        ]
      }
    },
    {
      "version": "2.0.2",
      "tag": "@kickstartds/storyblok-example_v2.0.2",
      "date": "Thu, 14 Mar 2024 13:15:38 GMT",
      "comments": {
        "dependency": [
          {
            "comment": "Updating dependency \"@kickstartds/jsonschema-utils\" to `3.0.2`"
          },
          {
            "comment": "Updating dependency \"@kickstartds/jsonschema2storyblok\" to `1.5.10`"
          }
        ]
      }
    },
    {
      "version": "2.0.1",
      "tag": "@kickstartds/storyblok-example_v2.0.1",
      "date": "Thu, 14 Mar 2024 12:45:31 GMT",
      "comments": {
        "dependency": [
          {
            "comment": "Updating dependency \"@kickstartds/jsonschema-utils\" to `3.0.1`"
          },
          {
            "comment": "Updating dependency \"@kickstartds/jsonschema2storyblok\" to `1.5.9`"
          }
        ]
      }
    },
    {
      "version": "2.0.0",
      "tag": "@kickstartds/storyblok-example_v2.0.0",
      "date": "Thu, 14 Mar 2024 12:11:35 GMT",
      "comments": {
        "major": [
          {
            "comment": "update to new kickstartDS releases"
          }
        ],
        "dependency": [
          {
            "comment": "Updating dependency \"@kickstartds/jsonschema-utils\" to `3.0.0`"
          },
          {
            "comment": "Updating dependency \"@kickstartds/jsonschema2storyblok\" to `1.5.8`"
          }
        ]
      }
    },
    {
      "version": "1.6.8",
      "tag": "@kickstartds/storyblok-example_v1.6.8",
      "date": "Sun, 11 Feb 2024 10:59:10 GMT",
      "comments": {
        "dependency": [
          {
            "comment": "Updating dependency \"@kickstartds/jsonschema2storyblok\" to `1.5.7`"
          }
        ]
      }
    },
    {
      "version": "1.6.7",
      "tag": "@kickstartds/storyblok-example_v1.6.7",
      "date": "Thu, 08 Feb 2024 17:23:24 GMT",
      "comments": {
        "patch": [
          {
            "comment": "update ksDS dependencies"
          }
        ]
      }
    },
    {
      "version": "1.6.6",
      "tag": "@kickstartds/storyblok-example_v1.6.6",
      "date": "Sun, 04 Feb 2024 16:52:43 GMT",
      "comments": {
        "dependency": [
          {
            "comment": "Updating dependency \"@kickstartds/jsonschema2storyblok\" to `1.5.6`"
          }
        ]
      }
    },
    {
      "version": "1.6.5",
      "tag": "@kickstartds/storyblok-example_v1.6.5",
      "date": "Tue, 30 Jan 2024 15:51:13 GMT",
      "comments": {
        "dependency": [
          {
            "comment": "Updating dependency \"@kickstartds/jsonschema2storyblok\" to `1.5.5`"
          }
        ]
      }
    },
    {
      "version": "1.6.4",
      "tag": "@kickstartds/storyblok-example_v1.6.4",
      "date": "Mon, 29 Jan 2024 19:29:51 GMT",
      "comments": {
        "dependency": [
          {
            "comment": "Updating dependency \"@kickstartds/jsonschema2storyblok\" to `1.5.4`"
          }
        ]
      }
    },
    {
      "version": "1.6.3",
      "tag": "@kickstartds/storyblok-example_v1.6.3",
      "date": "Mon, 29 Jan 2024 17:54:39 GMT",
      "comments": {
        "patch": [
          {
            "comment": "update to fixed converter"
          }
        ],
        "dependency": [
          {
            "comment": "Updating dependency \"@kickstartds/jsonschema2storyblok\" to `1.5.3`"
          }
        ]
      }
    },
    {
      "version": "1.6.2",
      "tag": "@kickstartds/storyblok-example_v1.6.2",
      "date": "Mon, 29 Jan 2024 13:41:37 GMT",
      "comments": {
        "patch": [
          {
            "comment": "update ksDS dependencies"
          }
        ],
        "dependency": [
          {
            "comment": "Updating dependency \"@kickstartds/jsonschema2storyblok\" to `1.5.2`"
          }
        ]
      }
    },
    {
      "version": "1.6.1",
      "tag": "@kickstartds/storyblok-example_v1.6.1",
      "date": "Tue, 23 Jan 2024 11:35:50 GMT",
      "comments": {
        "dependency": [
          {
            "comment": "Updating dependency \"@kickstartds/jsonschema2storyblok\" to `1.5.1`"
          }
        ]
      }
    },
    {
      "version": "1.6.0",
      "tag": "@kickstartds/storyblok-example_v1.6.0",
      "date": "Tue, 23 Jan 2024 10:56:23 GMT",
      "comments": {
        "minor": [
          {
            "comment": "update to improved converter, clean up ksDS dependencies"
          }
        ],
        "dependency": [
          {
            "comment": "Updating dependency \"@kickstartds/jsonschema-utils\" to `2.12.1`"
          },
          {
            "comment": "Updating dependency \"@kickstartds/jsonschema2storyblok\" to `1.5.0`"
          }
        ]
      }
    },
    {
      "version": "1.5.3",
      "tag": "@kickstartds/storyblok-example_v1.5.3",
      "date": "Sun, 21 Jan 2024 22:51:15 GMT",
      "comments": {
        "dependency": [
          {
            "comment": "Updating dependency \"@kickstartds/jsonschema2storyblok\" to `1.4.3`"
          }
        ]
      }
    },
    {
      "version": "1.5.2",
      "tag": "@kickstartds/storyblok-example_v1.5.2",
      "date": "Sun, 21 Jan 2024 22:45:57 GMT",
      "comments": {
        "dependency": [
          {
            "comment": "Updating dependency \"@kickstartds/jsonschema2storyblok\" to `1.4.2`"
          }
        ]
      }
    },
    {
      "version": "1.5.1",
      "tag": "@kickstartds/storyblok-example_v1.5.1",
      "date": "Sun, 21 Jan 2024 22:30:52 GMT",
      "comments": {
        "dependency": [
          {
            "comment": "Updating dependency \"@kickstartds/jsonschema2storyblok\" to `1.4.1`"
          }
        ]
      }
    },
    {
      "version": "1.5.0",
      "tag": "@kickstartds/storyblok-example_v1.5.0",
      "date": "Fri, 19 Jan 2024 10:59:21 GMT",
      "comments": {
        "minor": [
          {
            "comment": "fix naming of refs in schemas, update ksDS dependencies"
          }
        ],
        "dependency": [
          {
            "comment": "Updating dependency \"@kickstartds/jsonschema-utils\" to `2.12.0`"
          },
          {
            "comment": "Updating dependency \"@kickstartds/jsonschema2storyblok\" to `1.4.0`"
          }
        ]
      }
    },
    {
      "version": "1.4.1",
      "tag": "@kickstartds/storyblok-example_v1.4.1",
      "date": "Mon, 15 Jan 2024 13:01:48 GMT",
      "comments": {
        "patch": [
          {
            "comment": "update schema utils"
          }
        ],
        "dependency": [
          {
            "comment": "Updating dependency \"@kickstartds/jsonschema-utils\" to `2.11.1`"
          },
          {
            "comment": "Updating dependency \"@kickstartds/jsonschema2storyblok\" to `1.3.1`"
          }
        ]
      }
    },
    {
      "version": "1.4.0",
      "tag": "@kickstartds/storyblok-example_v1.4.0",
      "date": "Wed, 10 Jan 2024 08:06:43 GMT",
      "comments": {
        "minor": [
          {
            "comment": "use updated transformer"
          }
        ],
        "dependency": [
          {
            "comment": "Updating dependency \"@kickstartds/jsonschema-utils\" to `2.11.0`"
          },
          {
            "comment": "Updating dependency \"@kickstartds/jsonschema2storyblok\" to `1.3.0`"
          }
        ]
      }
    },
    {
      "version": "1.3.1",
      "tag": "@kickstartds/storyblok-example_v1.3.1",
      "date": "Mon, 04 Dec 2023 14:09:19 GMT",
      "comments": {
        "dependency": [
          {
            "comment": "Updating dependency \"@kickstartds/jsonschema2storyblok\" to `1.2.1`"
          }
        ]
      }
    },
    {
      "version": "1.3.0",
      "tag": "@kickstartds/storyblok-example_v1.3.0",
      "date": "Mon, 04 Dec 2023 11:43:19 GMT",
      "comments": {
        "minor": [
          {
            "comment": "update to reworked converter, update ds-agency"
          }
        ],
        "dependency": [
          {
            "comment": "Updating dependency \"@kickstartds/jsonschema-utils\" to `2.10.0`"
          },
          {
            "comment": "Updating dependency \"@kickstartds/jsonschema2storyblok\" to `1.2.0`"
          }
        ]
      }
    },
    {
      "version": "1.2.9",
      "tag": "@kickstartds/storyblok-example_v1.2.9",
      "date": "Thu, 23 Nov 2023 21:05:30 GMT",
      "comments": {
        "patch": [
          {
            "comment": "update example to use reworked converter"
          }
        ],
        "dependency": [
          {
            "comment": "Updating dependency \"@kickstartds/jsonschema-utils\" to `2.9.0`"
          },
          {
            "comment": "Updating dependency \"@kickstartds/jsonschema2storyblok\" to `1.1.0`"
          }
        ]
      }
    },
    {
      "version": "1.2.8",
      "tag": "@kickstartds/storyblok-example_v1.2.8",
      "date": "Thu, 02 Nov 2023 09:42:54 GMT",
      "comments": {
        "dependency": [
          {
            "comment": "Updating dependency \"@kickstartds/jsonschema2storyblok\" to `1.0.25`"
          }
        ]
      }
    },
    {
      "version": "1.2.7",
      "tag": "@kickstartds/storyblok-example_v1.2.7",
      "date": "Wed, 01 Nov 2023 23:02:38 GMT",
      "comments": {
        "dependency": [
          {
            "comment": "Updating dependency \"@kickstartds/jsonschema2storyblok\" to `1.0.24`"
          }
        ]
      }
    },
    {
      "version": "1.2.6",
      "tag": "@kickstartds/storyblok-example_v1.2.6",
      "date": "Wed, 01 Nov 2023 22:21:00 GMT",
      "comments": {
        "dependency": [
          {
            "comment": "Updating dependency \"@kickstartds/jsonschema2storyblok\" to `1.0.23`"
          }
        ]
      }
    },
    {
      "version": "1.2.5",
      "tag": "@kickstartds/storyblok-example_v1.2.5",
      "date": "Wed, 01 Nov 2023 22:17:41 GMT",
      "comments": {
        "dependency": [
          {
            "comment": "Updating dependency \"@kickstartds/jsonschema2storyblok\" to `1.0.22`"
          }
        ]
      }
    },
    {
      "version": "1.2.4",
      "tag": "@kickstartds/storyblok-example_v1.2.4",
      "date": "Wed, 01 Nov 2023 19:47:53 GMT",
      "comments": {
        "dependency": [
          {
            "comment": "Updating dependency \"@kickstartds/jsonschema2storyblok\" to `1.0.21`"
          }
        ]
      }
    },
    {
      "version": "1.2.3",
      "tag": "@kickstartds/storyblok-example_v1.2.3",
      "date": "Sun, 29 Oct 2023 11:05:45 GMT",
      "comments": {
        "dependency": [
          {
            "comment": "Updating dependency \"@kickstartds/jsonschema-utils\" to `2.8.0`"
          },
          {
            "comment": "Updating dependency \"@kickstartds/jsonschema2storyblok\" to `1.0.20`"
          }
        ]
      }
    },
    {
      "version": "1.2.2",
      "tag": "@kickstartds/storyblok-example_v1.2.2",
      "date": "Thu, 26 Oct 2023 21:35:49 GMT",
      "comments": {
        "dependency": [
          {
            "comment": "Updating dependency \"@kickstartds/jsonschema2storyblok\" to `1.0.19`"
          }
        ]
      }
    },
    {
      "version": "1.2.1",
      "tag": "@kickstartds/storyblok-example_v1.2.1",
      "date": "Thu, 26 Oct 2023 21:26:21 GMT",
      "comments": {
        "dependency": [
          {
            "comment": "Updating dependency \"@kickstartds/jsonschema-utils\" to `2.7.1`"
          },
          {
            "comment": "Updating dependency \"@kickstartds/jsonschema2storyblok\" to `1.0.18`"
          }
        ]
      }
    },
    {
      "version": "1.2.0",
      "tag": "@kickstartds/storyblok-example_v1.2.0",
      "date": "Wed, 18 Oct 2023 09:12:21 GMT",
      "comments": {
        "minor": [
          {
            "comment": "Add full set of example conversions"
          }
        ],
        "dependency": [
          {
            "comment": "Updating dependency \"@kickstartds/jsonschema2storyblok\" to `1.0.17`"
          }
        ]
      }
    },
    {
      "version": "1.1.0",
      "tag": "@kickstartds/storyblok-example_v1.1.0",
      "date": "Tue, 17 Oct 2023 21:48:32 GMT",
      "comments": {
        "minor": [
          {
            "comment": "Align all examples"
          }
        ]
      }
    },
    {
      "version": "1.0.17",
      "tag": "@kickstartds/storyblok-example_v1.0.17",
      "date": "Tue, 17 Oct 2023 20:52:25 GMT",
      "comments": {
        "patch": [
          {
            "comment": "Expand example to all usage scenarios"
          },
          {
            "comment": "Fix usage example"
          }
        ]
      }
    },
    {
      "version": "1.0.16",
      "tag": "@kickstartds/storyblok-example_v1.0.16",
      "date": "Tue, 17 Oct 2023 20:29:19 GMT",
      "comments": {
        "patch": [
          {
            "comment": "Use update jsonschema utils"
          }
        ],
        "dependency": [
          {
            "comment": "Updating dependency \"@kickstartds/jsonschema-utils\" to `2.7.0`"
          },
          {
            "comment": "Updating dependency \"@kickstartds/jsonschema2storyblok\" to `1.0.16`"
          }
        ]
      }
    },
    {
      "version": "1.0.15",
      "tag": "@kickstartds/storyblok-example_v1.0.15",
      "date": "Sun, 15 Oct 2023 10:08:47 GMT",
      "comments": {
        "dependency": [
          {
            "comment": "Updating dependency \"@kickstartds/jsonschema-utils\" to `2.6.0`"
          },
          {
            "comment": "Updating dependency \"@kickstartds/jsonschema2storyblok\" to `1.0.15`"
          }
        ]
      }
    },
    {
      "version": "1.0.14",
      "tag": "@kickstartds/storyblok-example_v1.0.14",
      "date": "Thu, 12 Oct 2023 12:44:39 GMT",
      "comments": {
        "patch": [
          {
            "comment": "use updated jsonschema utils"
          }
        ],
        "dependency": [
          {
            "comment": "Updating dependency \"@kickstartds/jsonschema-utils\" to `2.5.2`"
          },
          {
            "comment": "Updating dependency \"@kickstartds/jsonschema2storyblok\" to `1.0.14`"
          }
        ]
      }
    },
    {
      "version": "1.0.13",
      "tag": "@kickstartds/storyblok-example_v1.0.13",
      "date": "Wed, 11 Oct 2023 20:57:39 GMT",
      "comments": {
        "patch": [
          {
            "comment": "Use updated storyblok converter"
          }
        ],
        "dependency": [
          {
            "comment": "Updating dependency \"@kickstartds/jsonschema2storyblok\" to `1.0.13`"
          }
        ]
      }
    },
    {
      "version": "1.0.12",
      "tag": "@kickstartds/storyblok-example_v1.0.12",
      "date": "Wed, 11 Oct 2023 11:51:20 GMT",
      "comments": {
        "patch": [
          {
            "comment": "update to new jsonschema-utils release"
          }
        ],
        "dependency": [
          {
            "comment": "Updating dependency \"@kickstartds/jsonschema-utils\" to `2.5.1`"
          },
          {
            "comment": "Updating dependency \"@kickstartds/jsonschema2storyblok\" to `1.0.12`"
          }
        ]
      }
    },
    {
      "version": "1.0.11",
      "tag": "@kickstartds/storyblok-example_v1.0.11",
      "date": "Sat, 07 Oct 2023 18:54:59 GMT",
      "comments": {
        "dependency": [
          {
            "comment": "Updating dependency \"@kickstartds/jsonschema-utils\" to `2.5.0`"
          },
          {
            "comment": "Updating dependency \"@kickstartds/jsonschema2storyblok\" to `1.0.11`"
          }
        ]
      }
    },
    {
      "version": "1.0.10",
      "tag": "@kickstartds/storyblok-example_v1.0.10",
      "date": "Fri, 06 Oct 2023 13:43:55 GMT",
      "comments": {
        "dependency": [
          {
            "comment": "Updating dependency \"@kickstartds/jsonschema-utils\" to `2.4.18`"
          },
          {
            "comment": "Updating dependency \"@kickstartds/jsonschema2storyblok\" to `1.0.10`"
          }
        ]
      }
    },
    {
      "version": "1.0.9",
      "tag": "@kickstartds/storyblok-example_v1.0.9",
      "date": "Fri, 06 Oct 2023 13:08:52 GMT",
      "comments": {
        "dependency": [
          {
            "comment": "Updating dependency \"@kickstartds/jsonschema-utils\" to `2.4.17`"
          },
          {
            "comment": "Updating dependency \"@kickstartds/jsonschema2storyblok\" to `1.0.9`"
          }
        ]
      }
    },
    {
      "version": "1.0.8",
      "tag": "@kickstartds/storyblok-example_v1.0.8",
      "date": "Thu, 05 Oct 2023 10:51:41 GMT",
      "comments": {
        "patch": [
          {
            "comment": "add example for storyblok conversion"
          }
        ],
        "dependency": [
          {
            "comment": "Updating dependency \"@kickstartds/jsonschema-utils\" to `2.4.16`"
          },
          {
            "comment": "Updating dependency \"@kickstartds/jsonschema2storyblok\" to `1.0.8`"
          }
        ]
      }
    }
  ]
}
